sqltypes/__init__.py
sqltypes/__init__.pyi
sqltypes/jsons.py
sqltypes/meta.py
sqltypes/strings.py
sqltypes-0.1.9.dist-info/METADATA
sqltypes-0.1.9.dist-info/WHEEL
sqltypes-0.1.9.dist-info/top_level.txt
sqltypes-0.1.9.dist-info/RECORD
