Metadata-Version: 2.4
Name: sqltypes
Version: 0.1.9
Summary: Custom types for SQLModel/SQLalchemy
Author-email: Marcel Claramunt <marcel@marcelc.uk>
Project-URL: repo, https://github.com/marciclabas/sqltypes.git
Requires-Python: >=3.10
Requires-Dist: pydantic
Requires-Dist: sqlalchemy
Requires-Dist: lazy-loader
